README.md
setup.py
nsqworker/__init__.py
nsqworker/bootstrap.py
nsqworker/compat.py
nsqworker/initiator.py
nsqworker.egg-info/PKG-INFO
nsqworker.egg-info/SOURCES.txt
nsqworker.egg-info/dependency_links.txt
nsqworker.egg-info/requires.txt
nsqworker.egg-info/top_level.txt
nsqworker/workers/__init__.py
nsqworker/workers/worker.py
nsqworker/workers/demo/__init__.py
nsqworker/workers/demo/demo_pageview_worker.py