Metadata-Version: 1.1
Name: nsqworker
Version: 0.2.11
Summary: nsqworker is a skeletal code of one way to implement a nsq consumer in Python base on pynsq
Home-page: https://github.com/felinx/nsqworker
Author: Felinx Lee
Author-email: felinx.lee@gmail.com
License: http://www.apache.org/licenses/LICENSE-2.0
Platform: UNKNOWN
Classifier: Programming Language :: Python :: 2
Classifier: Programming Language :: Python :: 2.7
Classifier: Programming Language :: Python :: 3
Classifier: Programming Language :: Python :: 3.6
